multihash/__init__.py
multihash/codecs.py
multihash/funcs.py
multihash/multihash.py
multihash/version.py
pymultihash-0.8.2.dist-info/DESCRIPTION.rst
pymultihash-0.8.2.dist-info/METADATA
pymultihash-0.8.2.dist-info/RECORD
pymultihash-0.8.2.dist-info/WHEEL
pymultihash-0.8.2.dist-info/metadata.json
pymultihash-0.8.2.dist-info/top_level.txt
tests/__init__.py
tests/test_multihash.py
