Metadata-Version: 1.1
Name: pymultihash
Version: 0.8.2
Summary: Python implementation of the multihash specification
Home-page: https://github.com/ivilata/pymultihash
Author: Ivan Vilata-i-Balaguer
Author-email: ivan@selidor.net
License: MIT
Keywords: multihash hash digest format ASCII encoding
Platform: UNKNOWN
Classifier: Development Status :: 3 - Alpha
Classifier: Intended Audience :: Developers
Classifier: License :: OSI Approved :: MIT License
Classifier: Programming Language :: Python :: 3 :: Only
Classifier: Programming Language :: Python :: 3.4
Classifier: Programming Language :: Python :: 3.5
Classifier: Topic :: Security :: Cryptography
